README.txt
setup.py
xlutils3/__init__.py
xlutils3/copy.py
xlutils3/display.py
xlutils3/filter.py
xlutils3/margins.py
xlutils3/save.py
xlutils3/styles.py
xlutils3/view.py
xlutils3.egg-info/PKG-INFO
xlutils3.egg-info/SOURCES.txt
xlutils3.egg-info/dependency_links.txt
xlutils3.egg-info/top_level.txt
xlutils3.egg-info/zip-safe